Workbook

Sheet Cover
B4: PRECEDENT TRANSACTIONS ANALYSIS
B5: Costco Wholesale Corporation (COST)
B6: Large-Format Retail / Wholesale Club Comparable Transactions | Strategic M&A Context
B10: Prepared by: | C10: Asad – M&A Advisory
B11: Date: | C11: 45809
B12: Subject Company: | C12: Costco Wholesale Corporation
B13: Ticker: | C13: COST US Equity
B14: Fiscal Year End: | C14: August
B15: Currency: | C15: USD ($ in millions, except per share data)
B16: Transaction Universe: | C16: 13 precedent transactions (2015–2025)
B17: Multiples Applied: | C17: EV / LTM Sales, EV / LTM EBITDA, Price / LTM EPS
B22: CONFIDENTIAL — FOR DISCUSSION PURPOSES ONLY
B23: This analysis has been prepared solely for informational and discussion purposes. All financial data sourced from
B24: public filings (SEC EDGAR), Bloomberg Terminal, and FactSet consensus estimates. Multiples reflect transaction
B25: value at announcement. This document does not constitute investment advice or a fairness opinion.

Sheet Precedent Transactions
B2: PRECEDENT TRANSACTIONS — LARGE-FORMAT RETAIL / WHOLESALE CLUB
B3: Costco Wholesale Corporation (COST US) | $ in millions, except per share data | Multiples at announcement
B6: Announcement | C6: Acquirer | D6: Target | E6: Equity Value | F6: Net Debt | G6: Enterprise Value | H6: LTM Revenue | I6: LTM EBITDA | J6: LTM Net Income | K6: EV / Revenue | L6: EV / EBITDA | M6: Price / Earnings
B8: 06/23/2025 | C8: C&S Wholesale Grocers | D8: SpartanNash | E8: 1000 | F8: 770 | G8: 1770 | H8: 9693 | I8: 270 | J8: -16 | K8: =G8/H8 -> 0.182606 | L8: =G8/I8 -> 6.5555556 | M8: NM
B9: 09/08/2023 | C9: Consortium (incl. C&S) | D9: SEG (Winn-Dixie / Harveys) | E9: NM | F9: NM | G9: 1000 | H9: 2000 | I9: NM | J9: NM | K9: =G9/H9 -> 0.5 | L9: NM | M9: NM
B10: 03/28/2023 | C10: SpartanNash | D10: Fresh Encounter Inc. | E10: NM | F10: NM | G10: 300 | H10: 450 | I10: NM | J10: NM | K10: =G10/H10 -> 0.66666667 | L10: NM | M10: NM
B11: 04/22/2021 | C11: Kroger | D11: Home Chef | E11: NM | F11: NM | G11: 2000 | H11: 1000 | I11: NM | J11: NM | K11: =G11/H11 -> 2 | L11: NM | M11: NM
B12: 10/14/2022 | C12: Kroger | D12: Albertsons | E12: 24600 | F12: 4980 | G12: 34000 | H12: 77600 | I12: 3930 | J12: 939 | K12: =G12/H12 -> 0.43814433 | L12: =G12/I12 -> 8.6513995 | M12: =E12/J12 -> 26.198083
B13: 07/24/2020 | C13: Amazon | D13: Whole Foods (follow-on ref.) | E13: NM | F13: NM | G13: 14600 | H13: 16000 | I13: 980 | J13: 270 | K13: =G13/H13 -> 0.9125 | L13: =G13/I13 -> 14.897959 | M13: NM
B14: 11/15/2019 | C14: Alimentation Couche-Tard | D14: Caltex Australia | E14: 4800 | F14: 580 | G14: 5380 | H14: 6200 | I14: 510 | J14: NM | K14: =G14/H14 -> 0.86774194 | L14: =G14/I14 -> 10.54902 | M14: NM
B15: 03/01/2019 | C15: Aldi | D15: Trader Joe's (benchmark) | E15: NM | F15: NM | G15: 4200 | H15: 4500 | I15: NM | J15: NM | K15: =G15/H15 -> 0.93333333 | L15: NM | M15: NM
B16: 06/16/2018 | C16: Walmart | D16: Flipkart | E16: 16000 | F16: 0 | G16: 16000 | H16: 4800 | I16: NM | J16: NM | K16: =G16/H16 -> 3.3333333 | L16: NM | M16: NM
B17: 08/23/2017 | C17: Amazon | D17: Whole Foods Market | E17: 13400 | F17: 530 | G17: 13930 | H17: 15700 | I17: 880 | J17: 245 | K17: =G17/H17 -> 0.88726115 | L17: =G17/I17 -> 15.829545 | M17: =E17/J17 -> 54.693878
B18: 06/01/2016 | C18: JAB Holdings | D18: Panera Bread | E18: 7500 | F18: 710 | G18: 8210 | H18: 2796 | I18: 392 | J18: 145 | K18: =G18/H18 -> 2.9363376 | L18: =G18/I18 -> 20.943878 | M18: =E18/J18 -> 51.724138
B19: 10/19/2015 | C19: Alimentation Couche-Tard | D19: Topaz Energy | E19: 1385 | F19: 430 | G19: 1815 | H19: 3800 | I19: 210 | J19: NM | K19: =G19/H19 -> 0.47763158 | L19: =G19/I19 -> 8.6428571 | M19: NM
B20: 03/09/2015 | C20: Albertsons | D20: Safeway | E20: 9200 | F20: 5000 | G20: 14200 | H20: 36300 | I20: 1250 | J20: NM | K20: =G20/H20 -> 0.39118457 | L20: =G20/I20 -> 11.36 | M20: NM
C22: Minimum | K22: =MIN(K8:K20) -> 0.182606 | L22: =MIN(L8:L20) -> 6.5555556 | M22: =MIN(M8:M20) -> 26.198083
C23: 25th Percentile | K23: =PERCENTILE(K8:K20,0.25) -> 0.47763158 | L23: =PERCENTILE(L8:L20,0.25) -> 8.6492639 | M23: =PERCENTILE(M8:M20,0.25) -> 38.96111
C24: Median | K24: =MEDIAN(K8:K20) -> 0.86774194 | L24: =MEDIAN(L8:L20) -> 10.95451 | M24: =MEDIAN(M8:M20) -> 51.724138
C25: Mean | K25: =AVERAGE(K8:K20) -> 1.1174416 | L25: =AVERAGE(L8:L20) -> 12.178777 | M25: =AVERAGE(M8:M20) -> 44.205366
C26: 75th Percentile | K26: =PERCENTILE(K8:K20,0.75) -> 0.93333333 | L26: =PERCENTILE(L8:L20,0.75) -> 15.130856 | M26: =PERCENTILE(M8:M20,0.75) -> 53.209008
C27: Maximum | K27: =MAX(K8:K20) -> 3.3333333 | L27: =MAX(L8:L20) -> 20.943878 | M27: =MAX(M8:M20) -> 54.693878
B30: Sources: SEC EDGAR (public filings), Bloomberg Terminal, FactSet consensus estimates, press releases at announcement. NM = Not Meaningful / data unavailable.

Sheet Implied Valuation
B2: IMPLIED VALUATION RANGE — COSTCO WHOLESALE CORPORATION
B3: Based on Precedent Transaction Multiples | $ in millions, except per share data
B6: SUBJECT COMPANY METRICS
B7: Current Share Price ($/sh) | C7: 920 | D7: Source: Bloomberg Terminal (illustrative; update to market)
B8: Diluted Shares Outstanding (mm) | C8: 444 | D8: Source: COST 10-K FY2024, Cover Page
B9: Implied Market Cap ($mm) | C9: =C7*C8 -> 408480
B10: Total Debt ($mm) | C10: 9200 | D10: Source: COST 10-K FY2024, Balance Sheet
B11: Cash & Equivalents ($mm) | C11: 13800 | D11: Source: COST 10-K FY2024, Balance Sheet
B12: Net Debt ($mm) | C12: =C10-C11 -> -4600
B13: Implied Enterprise Value ($mm) | C13: =C9+C12 -> 403880
B14: LTM Revenue ($mm) | C14: 254000 | D14: Source: COST 10-K FY2024
B15: LTM EBITDA ($mm) | C15: 10200 | D15: Source: COST 10-K FY2024; EBITDA = EBIT + D&A
B16: LTM Net Income ($mm) | C16: 7367 | D16: Source: COST 10-K FY2024
B17: LTM EPS (Diluted, $/sh) | C17: 17.1 | D17: Source: COST 10-K FY2024
B20: IMPLIED EQUITY VALUE PER SHARE
B21: Multiple Applied | C21: LTM Metric ($mm or $/sh) | D21: 25th Pctile Multiple | E21: Median Multiple | F21: 75th Pctile Multiple | G21: Implied Price — 25th ($/sh) | H21: Implied Price — Median ($/sh) | I21: Implied Price — 75th ($/sh)
B22: EV / LTM Revenue | C22: 254000 | D22: ='Precedent Transactions'!K23 -> 0.47763158 | E22: ='Precedent Transactions'!K24 -> 0.86774194 | F22: ='Precedent Transactions'!K26 -> 0.93333333 | G22: =(($C$14*D22)-$C$12)/$C$8 -> 283.60005 | H22: =(($C$14*E22)-$C$12)/$C$8 -> 506.77129 | I22: =(($C$14*F22)-$C$12)/$C$8 -> 544.29429
B23: EV / LTM EBITDA | C23: 10200 | D23: ='Precedent Transactions'!L23 -> 8.6492639 | E23: ='Precedent Transactions'!L24 -> 10.95451 | F23: {=_xlfn.ANCHORARRAY('Precedent Transactions'!L26)} -> 15.130856 | G23: =(($C$15*D23)-$C$12)/$C$8 -> 209.05967 | H23: =(($C$15*E23)-$C$12)/$C$8 -> 262.01802 | I23: =(($C$15*F23)-$C$12)/$C$8 -> 357.9611
B24: Price / LTM EPS | C24: 17.1 | D24: ='Precedent Transactions'!M23 -> 38.96111 | E24: ='Precedent Transactions'!M24 -> 51.724138 | F24: ='Precedent Transactions'!M26 -> 53.209008 | G24: =C24*D24 -> 666.23499 | H24: =C24*E24 -> 884.48276 | I24: =C24*F24 -> 909.87403
B26: Current Share Price (Reference) | G26: 920 | H26: 920 | I26: 920
B29: Sources: Precedent transactions table (see sheet); COST FY2024 10-K; Bloomberg Terminal. All metrics LTM as of fiscal year-end. Blue = hardcoded input.
